{
  "ROLES": [
    {
      "id": "7249",
      "name": "customer"
    }
  ],
  "USERS": [
    {
      "id": "6cbc",
      "name": "maria",
      "identification": "1111111",
      "phone": "3161361990",
      "pasword": "321"
    },
    {
      "id": "d53f",
      "name": "jaime",
      "identification": "1111111",
      "phone": "3161361990",
      "direccion": "calle 51",
      "email": "messiembappe@gmail.com",
      "contraseña": "0323",
      "rolId": "7249"
    }
  ],
  "PETS": [
    {
      
    }
  ]
}